Workbook
Name Locations: Table1[Destination]
Name ShippingData: Table1[#All]
Name Slicer_Status: #N/A

Sheet GlobalSales
A1: OrderID | B1: Date | C1: Country | D1: Product | E1: Quantity | F1: UnitPrice | G1: Total
A2: 2001 | B2: 05/10/2026 | C2: USA | D2: Widget A | E2: 150 | F2: 12.5 | G2: =GlobalSales!$E2*GlobalSales!$F2 -> 1875
A3: 2002 | B3: 46331 | C3: UK | D3: Widget B | E3: 85 | F3: 25 | G3: =GlobalSales!$E3*GlobalSales!$F3 -> 2125
A4: 2003 | B4: 05/11/2026 | C4: USA | D4: Widget A | E4: 200 | F4: 12.5 | G4: =GlobalSales!$E4*GlobalSales!$F4 -> 2500
A5: 2004 | B5: 05/12/2026 | C5: Germany | D5: Widget C | E5: 45 | F5: 100 | G5: =GlobalSales!$E5*GlobalSales!$F5 -> 4500
A6: 2005 | B6: 05/13/2026 | C6: UK | D6: Widget B | E6: 120 | F6: 25 | G6: =GlobalSales!$E6*GlobalSales!$F6 -> 3000
A7: 2006 | B7: 05/14/2026 | C7: France | D7: Widget A | E7: 300 | F7: 12 | G7: =GlobalSales!$E7*GlobalSales!$F7 -> 3600
A8: 2007 | B8: 05/14/2026 | C8: Germany | D8: Widget C | E8: 60 | F8: 100 | G8: =GlobalSales!$E8*GlobalSales!$F8 -> 6000
A9: 2008 | B9: 05/15/2026 | C9: USA | D9: Widget B | E9: 90 | F9: 26 | G9: =GlobalSales!$E9*GlobalSales!$F9 -> 2340

Sheet HR_Records
A1: EmpID | B1: LastName | C1: FirstName | D1: Dept | E1: YearsOfService | F1: Salary | G1: FullName | H1: Bonus
A2: E101 | B2: Smith | C2: John | D2: Sales | E2: 3 | F2: 45000 | G2: =_xlfn.CONCAT(HR_Records[[#This Row],[FirstName]], " ",HR_Records[[#This Row],[LastName]]) -> John Smith | H2: =IF(HR_Records[[#This Row],[YearsOfService]]>5,HR_Records[[#This Row],[Salary]]*0.1,HR_Records[[#This Row],[Salary]]*0.05) -> 2250
A3: E102 | B3: Doe | C3: Jane | D3: IT | E3: 6 | F3: 75000 | G3: =_xlfn.CONCAT(HR_Records[[#This Row],[FirstName]], " ",HR_Records[[#This Row],[LastName]]) -> Jane Doe | H3: =IF(HR_Records[[#This Row],[YearsOfService]]>5,HR_Records[[#This Row],[Salary]]*0.1,HR_Records[[#This Row],[Salary]]*0.05) -> 7500
A4: E103 | B4: Brown | C4: William | D4: HR | E4: 2 | F4: 42000 | G4: =_xlfn.CONCAT(HR_Records[[#This Row],[FirstName]], " ",HR_Records[[#This Row],[LastName]]) -> William Brown | H4: =IF(HR_Records[[#This Row],[YearsOfService]]>5,HR_Records[[#This Row],[Salary]]*0.1,HR_Records[[#This Row],[Salary]]*0.05) -> 2100
A5: E104 | B5: Johnson | C5: Michael | D5: Sales | E5: 8 | F5: 52000 | G5: =_xlfn.CONCAT(HR_Records[[#This Row],[FirstName]], " ",HR_Records[[#This Row],[LastName]]) -> Michael Johnson | H5: =IF(HR_Records[[#This Row],[YearsOfService]]>5,HR_Records[[#This Row],[Salary]]*0.1,HR_Records[[#This Row],[Salary]]*0.05) -> 5200
A6: E105 | B6: Davis | C6: Emily | D6: IT | E6: 1 | F6: 68000 | G6: =_xlfn.CONCAT(HR_Records[[#This Row],[FirstName]], " ",HR_Records[[#This Row],[LastName]]) -> Emily Davis | H6: =IF(HR_Records[[#This Row],[YearsOfService]]>5,HR_Records[[#This Row],[Salary]]*0.1,HR_Records[[#This Row],[Salary]]*0.05) -> 3400
A7: E106 | B7: Wilson | C7: Jessica | D7: Marketing | E7: 5 | F7: 60000 | G7: =_xlfn.CONCAT(HR_Records[[#This Row],[FirstName]], " ",HR_Records[[#This Row],[LastName]]) -> Jessica Wilson | H7: =IF(HR_Records[[#This Row],[YearsOfService]]>5,HR_Records[[#This Row],[Salary]]*0.1,HR_Records[[#This Row],[Salary]]*0.05) -> 3000
A8: E107 | B8: Moore | C8: David | D8: Sales | E8: 10 | F8: 58000 | G8: =_xlfn.CONCAT(HR_Records[[#This Row],[FirstName]], " ",HR_Records[[#This Row],[LastName]]) -> David Moore | H8: =IF(HR_Records[[#This Row],[YearsOfService]]>5,HR_Records[[#This Row],[Salary]]*0.1,HR_Records[[#This Row],[Salary]]*0.05) -> 5800
A11: Company Portal

Sheet Logistics
A1: ShipmentID | B1: Warehouse | C1: Destination | D1: Weight | E1: Status | F1: Cost | G1: Trend
A2: S901 | B2: North | C2: London | D2: 450 | E2: Delivered | F2: 120 | H2: =COUNTIFS(Table1[Destination],"London",Table1[Status],"Delivered") -> 2
A3: S902 | B3: South | C3: Paris | D3: 800 | E3: In Transit | F3: 250
A4: S904 | B4: East | C4: London | D4: 550 | E4: Delivered | F4: 145
A5: =SUBTOTAL(103,Table1[ShipmentID]) -> 3

Sheet MarketingCampaign
A1: CampaignName | B1: Platform | C1: Budget | D1: Spend | E1: Conversions | F1: CPA
A2: BrandAware | B2: Facebook | C2: 8000 | D2: 7500 | E2: 450 | F2: 16.67
A3: SummerSale | B3: Google | C3: 15000 | D3: 14500 | E3: 1200 | F3: 12.08
A4: Retargeting | B4: Google | C4: 5000 | D4: 5200 | E4: 800 | F4: 6.5
A5: B2B_Leads | B5: LinkedIn | C5: 12000 | D5: 10000 | E5: 150 | F5: 66.67
A6: GenZ_Promo | B6: TikTok | C6: 6000 | D6: 5800 | E6: 900 | F6: 6.44

Sheet Summary_Setup
A1: Category | B1: Q1 | C1: Q2 | D1: Q3 | E1: Q4 | F1: Total | G1: % of Total
A2: Electronics | B2: 45000 | C2: 42000 | D2: 51000 | E2: 68000 | F2: =SUM(Summary_Setup[[#This Row],[Q1]:[Q4]]) -> 206000 | G2: =Summary_Setup[[#This Row],[Total]]/Summary_Setup[[#Totals],[Total]] -> 0.40711462
A3: Furniture | B3: 22000 | C3: 24000 | D3: 23000 | E3: 31000 | F3: =SUM(Summary_Setup[[#This Row],[Q1]:[Q4]]) -> 100000 | G3: =Summary_Setup[[#This Row],[Total]]/Summary_Setup[[#Totals],[Total]] -> 0.19762846
A4: Accessories | B4: 15000 | C4: 18000 | D4: 16000 | E4: 25000 | F4: =SUM(Summary_Setup[[#This Row],[Q1]:[Q4]]) -> 74000 | G4: =Summary_Setup[[#This Row],[Total]]/Summary_Setup[[#Totals],[Total]] -> 0.14624506
A5: Services | B5: 30000 | C5: 31000 | D5: 30000 | E5: 35000 | F5: =SUM(Summary_Setup[[#This Row],[Q1]:[Q4]]) -> 126000 | G5: =Summary_Setup[[#This Row],[Total]]/Summary_Setup[[#Totals],[Total]] -> 0.24901186
F6: =SUM(Summary_Setup[Total]) -> 506000
